{
  "quantum-bound-states.title": {
    "value": "Quantum Bound States"
  },
  "screen.oneWell": {
    "value": "One Well"
  },
  "screen.superposition": {
    "value": "Superposition"
  },
  "screen.twoWells": {
    "value": "Two Wells"
  },
  "screen.manyWells": {
    "value": "Many Wells"
  },
  "phaseFeatureControl": {
    "label": {
      "value": "Wave Function Phase"
    },
    "description": {
      "value": "Adds a Phase checkbox to control panels for showing and hiding the phase of the wave function."
    }
  },
  "potentialEnergy": {
    "value": "Potential Energy"
  },
  "totalEnergy": {
    "value": "Total Energy"
  },
  "position_nm": {
    "value": "Position (nm)"
  },
  "energy_eV": {
    "value": "Energy (eV)"
  },
  "averageProbabilityDensityOfBand": {
    "value": "Average Probability<br>Density of Band"
  },
  "probabilityDensity": {
    "value": "Probability Density"
  },
  "waveFunction": {
    "value": "Wave Function"
  },
  "display": {
    "value": "Display"
  },
  "properties": {
    "value": "Properties"
  },
  "showValues": {
    "value": "Show Values"
  },
  "realPart": {
    "value": "Real Part"
  },
  "imaginaryPart": {
    "value": "Imaginary Part"
  },
  "magnitude": {
    "value": "Magnitude"
  },
  "phase": {
    "value": "Phase"
  },
  "magnifierTool": {
    "value": "Magnifier Tool"
  },
  "referenceLine": {
    "value": "Reference Line"
  },
  "a11y": {
    "oneWellScreen": {
      "screenButtonsHelpText": {
        "value": "TODO.oneWellScreen.screenButtonsHelpText"
      },
      "screenSummary": {
        "playArea": {
          "value": "TODO.oneWellScreen.screenSummary.playArea"
        },
        "controlArea": {
          "value": "TODO.oneWellScreen.screenSummary.controlArea"
        },
        "currentDetails": {
          "value": "TODO.oneWellScreen.screenSummary.currentDetails"
        },
        "interactionHint": {
          "value": "TODO.oneWellScreen.screenSummary.interactionHint"
        }
      }
    },
    "twoWellsScreen": {
      "screenButtonsHelpText": {
        "value": "TODO.twoWellsScreen.screenButtonsHelpText"
      },
      "screenSummary": {
        "playArea": {
          "value": "TODO.twoWellsScreen.screenSummary.playArea"
        },
        "controlArea": {
          "value": "TODO.twoWellsScreen.screenSummary.controlArea"
        },
        "currentDetails": {
          "value": "TODO.twoWellsScreen.screenSummary.currentDetails"
        },
        "interactionHint": {
          "value": "TODO.twoWellsScreen.screenSummary.interactionHint"
        }
      }
    },
    "manyWellsScreen": {
      "screenButtonsHelpText": {
        "value": "TODO.manyWellsScreen.screenButtonsHelpText"
      },
      "screenSummary": {
        "playArea": {
          "value": "TODO.manyWellsScreen.screenSummary.playArea"
        },
        "controlArea": {
          "value": "TODO.manyWellsScreen.screenSummary.controlArea"
        },
        "currentDetails": {
          "value": "TODO.manyWellsScreen.screenSummary.currentDetails"
        },
        "interactionHint": {
          "value": "TODO.manyWellsScreen.screenSummary.interactionHint"
        }
      }
    },
    "superpositionScreen": {
      "screenButtonsHelpText": {
        "value": "TODO.oneWellScreen.screenButtonsHelpText"
      },
      "screenSummary": {
        "playArea": {
          "value": "TODO.superpositionScreen.screenSummary.playArea"
        },
        "controlArea": {
          "value": "TODO.superpositionScreen.screenSummary.controlArea"
        },
        "currentDetails": {
          "value": "TODO.superpositionScreen.screenSummary.currentDetails"
        },
        "interactionHint": {
          "value": "TODO.superpositionScreen.screenSummary.interactionHint"
        }
      }
    },
    "realPartCheckbox": {
      "accessibleHelpText": {
        "value": "TODO.realPartCheckbox.accessibleHelpText"
      }
    },
    "imaginaryPartCheckbox": {
      "accessibleHelpText": {
        "value": "TODO.imaginaryPartCheckbox.accessibleHelpText"
      }
    },
    "magnitudeCheckbox": {
      "accessibleHelpText": {
        "value": "TODO.magnitudeCheckbox.accessibleHelpText"
      }
    },
    "phaseCheckbox": {
      "accessibleHelpText": {
        "value": "TODO.phaseCheckbox.accessibleHelpText"
      }
    },
    "magnifierToolCheckbox": {
      "accessibleHelpText": {
        "value": "TODO.magnifierToolCheckbox.accessibleHelpText"
      },
      "accessibleContextResponseChecked": {
        "value": "Magnifier Tool shown."
      },
      "accessibleContextResponseUnchecked": {
        "value": "Magnifier Tool hidden."
      }
    },
    "referenceLineCheckbox": {
      "accessibleHelpText": {
        "value": "TODO.referenceLineCheckbox.accessibleHelpText"
      },
      "accessibleContextResponseChecked": {
        "value": "Reference Line shown."
      },
      "accessibleContextResponseUnchecked": {
        "value": "Reference Line hidden."
      }
    },
    "graphTypeRadioButtonGroup": {
      "accessibleName": {
        "value": "Graph Type"
      },
      "accessibleHelpText": {
        "value": "TODO.graphTypeRadioButtonGroup.accessibleHelpText"
      },
      "averageProbabilityDensityOfBandRadioButton": {
        "accessibleHelpText": {
          "value": "TODO.averageProbabilityDensityOfBandRadioButton.accessibleHelpText"
        }
      },
      "probabilityDensityRadioButton": {
        "accessibleHelpText": {
          "value": "TODO.probabilityDensityRadioButton.accessibleHelpText"
        }
      },
      "wavefunctionRadioButton": {
        "accessibleHelpText": {
          "value": "TODO.wavefunctionRadioButton.accessibleHelpText"
        }
      }
    },
    "referenceLineHandleNode": {
      "accessibleName": {
        "value": "Reference Line handle"
      },
      "accessibleHelpText": {
        "value": "TODO.referenceLineHandleNode.accessibleHelpText"
      },
      "accessibleObjectResponse": {
        "value": "TODO.referenceLineHandleNode.accessibleObjectResponse"
      }
    }
  }
}